{
  "main": {
    "id": "01a21c84347731a5",
    "type": "split",
    "children": [
      {
        "id": "29ed558ac943aaa7",
        "type": "tabs",
        "children": [
          {
            "id": "0b61050d579c2b1f",
            "type": "leaf",
            "state": {
              "type": "empty",
              "state": {}
            }
          }
        ]
      }
    ],
    "direction": "vertical"
  },
  "left": {
    "id": "8d2128562177354c",
    "type": "split",
    "children": [
      {
        "id": "6efc2e3165814efc",
        "type": "tabs",
        "children": [
          {
            "id": "4fddb5355e592c76",
            "type": "leaf",
            "state": {
              "type": "file-explorer",
              "state": {
                "sortOrder": "alphabetical"
              }
            }
          },
          {
            "id": "381f64e2ac356a76",
            "type": "leaf",
            "state": {
              "type": "search",
              "state": {
                "query": "",
                "matchingCase": false,
                "explainSearch": false,
                "collapseAll": false,
                "extraContext": false,
                "sortOrder": "alphabetical"
              }
            }
          },
          {
            "id": "79fa4d4aef6d42d6",
            "type": "leaf",
            "state": {
              "type": "bookmarks",
              "state": {}
            }
          }
        ]
      }
    ],
    "direction": "horizontal",
    "width": 300
  },
  "right": {
    "id": "c30a18dbbe5c888b",
    "type": "split",
    "children": [
      {
        "id": "2010751f2b554aed",
        "type": "tabs",
        "children": [
          {
            "id": "9c768b0b7a4cbea9",
            "type": "leaf",
            "state": {
              "type": "backlink",
              "state": {
                "collapseAll": false,
                "extraContext": false,
                "sortOrder": "alphabetical",
                "showSearch": false,
                "searchQuery": "",
                "backlinkCollapsed": false,
                "unlinkedCollapsed": true
              }
            }
          },
          {
            "id": "6c7091fd93e60a69",
            "type": "leaf",
            "state": {
              "type": "outgoing-link",
              "state": {
                "linksCollapsed": false,
                "unlinkedCollapsed": true
              }
            }
          },
          {
            "id": "7b653fffee659efa",
            "type": "leaf",
            "state": {
              "type": "tag",
              "state": {
                "sortOrder": "frequency",
                "useHierarchy": true
              }
            }
          },
          {
            "id": "e9e6dd1d7a540ca6",
            "type": "leaf",
            "state": {
              "type": "outline",
              "state": {}
            }
          }
        ]
      }
    ],
    "direction": "horizontal",
    "width": 300,
    "collapsed": true
  },
  "left-ribbon": {
    "hiddenItems": {
      "switcher:Open quick switcher": false,
      "graph:Open graph view": false,
      "canvas:Create new canvas": false,
      "daily-notes:Open today's daily note": false,
      "templates:Insert template": false,
      "command-palette:Open command palette": false
    }
  },
  "active": "0b61050d579c2b1f",
  "lastOpenFiles": [
    "build/app/intermediates/symbol_list_with_package_name/debug/package-aware-r.txt",
    "build/app/intermediates/runtime_symbol_list/debug/R.txt",
    "build/app/intermediates/compile_and_runtime_not_namespaced_r_class_jar/debug/R.jar",
    "build/app/intermediates/project_dex_archive/debug/out/893055de1af0e83c44a85dd59de19342e8bf8c4b156e7347c23ade2a24b12d5b_0.jar",
    "build/app/intermediates/project_dex_archive/debug/out/893055de1af0e83c44a85dd59de19342e8bf8c4b156e7347c23ade2a24b12d5b_1.jar",
    "build/app/intermediates/project_dex_archive/debug/out/893055de1af0e83c44a85dd59de19342e8bf8c4b156e7347c23ade2a24b12d5b_2.jar",
    "build/app/intermediates/project_dex_archive/debug/out/893055de1af0e83c44a85dd59de19342e8bf8c4b156e7347c23ade2a24b12d5b_3.jar",
    "build/app/intermediates/incremental/debug-mergeJavaRes/zip-cache/6ziVrtsbucYzhb19yI8jDsPLT7c=",
    "build/app/intermediates/incremental/debug-mergeJavaRes/zip-cache/9psIhPPfp1BIS3dpUg64RQpJHbc=",
    "build/app/intermediates/incremental/debug-mergeJavaRes/zip-cache/a3x6c46qkkodGkJnMK9F7ggb8gc=",
    "build/app/intermediates/incremental/debug-mergeJavaRes/zip-cache/bEpxrY8V3oYMFKyfPJU6vhvjfAY=",
    "README.md",
    "README (2).md"
  ]
}